password_strength/__init__.py
password_strength/policy.py
password_strength/stats.py
password_strength/tests.py
password_strength/tests_base.py
password_strength-0.0.3.post2.dist-info/LICENSE
password_strength-0.0.3.post2.dist-info/METADATA
password_strength-0.0.3.post2.dist-info/WHEEL
password_strength-0.0.3.post2.dist-info/top_level.txt
password_strength-0.0.3.post2.dist-info/RECORD
