Metadata-Version: 2.1
Name: password-strength
Version: 0.0.3.post2
Summary:  Password strength and validation 
Home-page: https://github.com/kolypto/py-password-strength
Author: Mark Vartanyan
Author-email: kolypto@gmail.com
License: BSD
Keywords: password,strength,policy,security
Platform: any
Classifier: Development Status :: 5 - Production/Stable
Classifier: Intended Audience :: Developers
Classifier: Natural Language :: English
Classifier: Operating System :: OS Independent
Classifier: Programming Language :: Python :: 2
Classifier: Programming Language :: Python :: 3
Classifier: Topic :: Software Development :: Libraries :: Python Modules
